bits/__init__.py
bits/cloudaccounts/__init__.py
bits/cloudaccounts/amazon.py
bits/cloudaccounts/api.py
bits/cloudaccounts/bitsdb.py
bits/cloudaccounts/firestore.py
bits/cloudaccounts/google.py
tests/__init__.py
tests/test_amazon.py
tests/test_api.py
tests/test_bitsdb.py
tests/test_firestore.py
tests/test_google.py
tests/test_init.py
bits_cloudaccounts-1.0.17.dist-info/METADATA
bits_cloudaccounts-1.0.17.dist-info/WHEEL
bits_cloudaccounts-1.0.17.dist-info/top_level.txt
bits_cloudaccounts-1.0.17.dist-info/RECORD
