Metadata-Version: 2.1
Name: bits-cloudaccounts
Version: 1.0.17
Summary: BITS Cloud Accounts
Home-page: UNKNOWN
Author: Lukas Karlsson
Author-email: karlsson@broadinstitute.org
License: Apache Software License
Platform: UNKNOWN
Requires-Dist: google-cloud-firestore
